baldaquin/__init__.py
baldaquin/__qt__.py
baldaquin/_version.py
baldaquin/app.py
baldaquin/arduino_.py
baldaquin/buf.py
baldaquin/cli.py
baldaquin/config.py
baldaquin/egu.py
baldaquin/env.py
baldaquin/event.py
baldaquin/gui.py
baldaquin/hsk.py
baldaquin/logging_.py
baldaquin/pkt.py
baldaquin/plt_.py
baldaquin/profile.py
baldaquin/runctrl.py
baldaquin/serial_.py
baldaquin/timeline.py
baldaquin/typing_.py
baldaquin/graphics/icons/material3/chat_FILL0_wght400_GRAD0_opsz48.svg
baldaquin/graphics/icons/material3/drive_folder_upload_FILL0_wght400_GRAD0_opsz48.svg
baldaquin/graphics/icons/material3/file_download_FILL0_wght400_GRAD0_opsz48.svg
baldaquin/graphics/icons/material3/file_open_FILL0_wght400_GRAD0_opsz48.svg
baldaquin/graphics/icons/material3/file_upload_FILL0_wght400_GRAD0_opsz48.svg
baldaquin/graphics/icons/material3/hub_FILL0_wght400_GRAD0_opsz48.svg
baldaquin/graphics/icons/material3/lan_FILL0_wght400_GRAD0_opsz48.svg
baldaquin/graphics/icons/material3/login_FILL0_wght400_GRAD0_opsz48.svg
baldaquin/graphics/icons/material3/logout_FILL0_wght400_GRAD0_opsz48.svg
baldaquin/graphics/icons/material3/pause_FILL0_wght400_GRAD0_opsz48.svg
baldaquin/graphics/icons/material3/play_arrow_FILL0_wght400_GRAD0_opsz48.svg
baldaquin/graphics/icons/material3/sensors_FILL0_wght400_GRAD0_opsz48.svg
baldaquin/graphics/icons/material3/share_FILL0_wght400_GRAD0_opsz48.svg
baldaquin/graphics/icons/material3/stop_FILL0_wght400_GRAD0_opsz48.svg
baldaquin/graphics/icons/material3/upload_file_FILL0_wght400_GRAD0_opsz48.svg
baldaquin/graphics/skins/default.qss
baldaquin/plasduino/__init__.py
baldaquin/plasduino/common.py
baldaquin/plasduino/protocol.py
baldaquin/plasduino/shields.py
baldaquin/plasduino/sketches.py
baldaquin/plasduino/apps/plasduino_pendulum.py
baldaquin/plasduino/apps/plasduino_pendulumview.py
baldaquin/plasduino/apps/plasduino_tempmonitor.py
baldaquin/plasduino/sensors/NXFT15XH103FA2B.dat
baldaquin/plasduino/sketches/analog_sampling.hex
baldaquin-0.10.2.dist-info/METADATA
baldaquin-0.10.2.dist-info/WHEEL
baldaquin-0.10.2.dist-info/entry_points.txt
baldaquin-0.10.2.dist-info/licenses/LICENSE
baldaquin-0.10.2.dist-info/RECORD
